{"cameraMode":{"drawMode":0,"name":"Shaded","section":"Shading Mode"},"sceneLighting":true,"audioPlay":false,"sceneViewState":{"showFog":true,"showMaterialUpdate":false,"showSkybox":true,"showFlares":true,"showImageEffects":true,"showParticleSystems":true,"showVisualEffectGraphs":true,"m_FxEnabled":true},"in2DMode":false,"pivot":{"x":14.5625,"y":0.5847642421722412,"z":-12.176000595092774},"rotation":{"x":0.5805001258850098,"y":0.055636730045080188,"z":-0.04358991980552673,"w":0.8117819428443909},"size":1.7198604345321656,"orthographic":false}